flake8_pep3101.py
flake8_pep3101-2.0.0.dist-info/LICENSE
flake8_pep3101-2.0.0.dist-info/METADATA
flake8_pep3101-2.0.0.dist-info/WHEEL
flake8_pep3101-2.0.0.dist-info/entry_points.txt
flake8_pep3101-2.0.0.dist-info/top_level.txt
flake8_pep3101-2.0.0.dist-info/RECORD
