Metadata-Version: 2.1
Name: flake8-pep3101
Version: 2.0.0
Summary: Checks for old string formatting.
Home-page: https://github.com/gforcada/flake8-pep3101
Author: Gil Forcada
Author-email: gil.gnome@gmail.com
License: GPL version 2
Keywords: pep8 pycodestyle flake8 python string formatting
Platform: UNKNOWN
Classifier: Development Status :: 5 - Production/Stable
Classifier: Environment :: Console
Classifier: Framework :: Flake8
Classifier: Intended Audience :: Developers
Classifier: License :: OSI Approved :: GNU General Public License v2 (GPLv2)
Classifier: Operating System :: OS Independent
Classifier: Programming Language :: Python
Classifier: Programming Language :: Python :: 3
Classifier: Programming Language :: Python :: 3 :: Only
Classifier: Programming Language :: Python :: 3.7
Classifier: Programming Language :: Python :: 3.8
Classifier: Programming Language :: Python :: 3.9
Classifier: Programming Language :: Python :: 3.10
Classifier: Programming Language :: Python :: Implementation :: CPython
Classifier: Programming Language :: Python :: Implementation :: PyPy
Classifier: Topic :: Software Development
Classifier: Topic :: Software Development :: Quality Assurance
License-File: LICENSE
Requires-Dist: flake8
Provides-Extra: test
Requires-Dist: pytest ; extra == 'test'
